auto_period_finder/__init__.py
auto_period_finder/finder.py
auto_period_finder-0.0.11.dist-info/LICENSE
auto_period_finder-0.0.11.dist-info/METADATA
auto_period_finder-0.0.11.dist-info/WHEEL
auto_period_finder-0.0.11.dist-info/RECORD
