Metadata-Version: 2.1
Name: auto-period-finder
Version: 0.0.11
Summary: An autocorrelation function-based seasonality periods automatic finder for univariate time series.
Home-page: https://github.com/iskandergaba/auto-period-finder
License: MIT
Keywords: time,series,forecast,analysis,seasonality,trend,decomposition
Author: Iskander Gaba
Author-email: iskander@hey.com
Requires-Python: >=3.10,<4.0
Classifier: License :: OSI Approved :: MIT License
Classifier: Programming Language :: Python :: 3
Classifier: Programming Language :: Python :: 3.10
Classifier: Programming Language :: Python :: 3.11
Classifier: Programming Language :: Python :: 3.12
Requires-Dist: statsmodels (>=0.14.1,<0.15.0)
Project-URL: Repository, https://github.com/iskandergaba/auto-period-finder
